motorpy/__init__.py
motorpy/base.py
motorpy/actions/__init__.py
motorpy/api/__init__.py
motorpy/api/core.py
motorpy/api/exceptions.py
motorpy/api/org.py
motorpy/auth/__init__.py
motorpy/auth/abc.py
motorpy/auth/apikey.py
motorpy/auth/core.py
motorpy/auth/driver.py
motorpy/auth/exceptions.py
motorpy/auth/jwt.py
motorpy/auth/user.py
motorpy/auth/tests/__init__.py
motorpy/auth/tests/test_api_key.py
motorpy/auth/tests/test_drivers.py
motorpy/auth/tests/test_users.py
motorpy/drivers/__init__.py
motorpy/drivers/core.py
motorpy/fleets/__init__.py
motorpy/fleets/core.py
motorpy/models/__init__.py
motorpy/models/custom.py
motorpy/models/billing/__init__.py
motorpy/models/billing/accounts.py
motorpy/models/billing/events.py
motorpy/models/billing/tests/__init__.py
motorpy/models/billing/tests/test_accounts.py
motorpy/models/billing/tests/test_api_handler.py
motorpy/models/billing/tests/test_events.py
motorpy/models/constants/__init__.py
motorpy/models/constants/lang.py
motorpy/models/drivers/__init__.py
motorpy/models/drivers/tests/__init__.py
motorpy/models/drivers/tests/test_driver.py
motorpy/models/fleets/__init__.py
motorpy/models/fleets/assigned.py
motorpy/models/fleets/drivers.py
motorpy/models/fleets/vehicles.py
motorpy/models/fleets/tests/__init__.py
motorpy/models/fleets/tests/test_fleets.py
motorpy/models/policy/__init__.py
motorpy/models/policy/_fields.py
motorpy/models/policy/actions.py
motorpy/models/policy/base.py
motorpy/models/policy/nested.py
motorpy/models/policy/org_config.py
motorpy/models/policy/update.py
motorpy/models/policy/approval/__init__.py
motorpy/models/policy/cancellation/__init__.py
motorpy/models/policy/config/__init__.py
motorpy/models/policy/config/base.py
motorpy/models/policy/config/generation.py
motorpy/models/policy/config/geofence.py
motorpy/models/policy/config/terms.py
motorpy/models/policy/contribution/__init__.py
motorpy/models/policy/driver/__init__.py
motorpy/models/policy/duration/__init__.py
motorpy-0.1.6.dist-info/LICENSE
motorpy-0.1.6.dist-info/METADATA
motorpy-0.1.6.dist-info/WHEEL
motorpy-0.1.6.dist-info/entry_points.txt
motorpy-0.1.6.dist-info/top_level.txt
motorpy-0.1.6.dist-info/RECORD
