Metadata-Version: 2.1
Name: motorpy
Version: 0.1.6
Summary: Inaza Motor Python SDK
Home-page: https://github.com/nSurely/motorpy/
Author: Inaza
Requires-Python: >=3.7
License-File: LICENSE
Requires-Dist: pydantic (~=1.9.2)
Requires-Dist: aiohttp (~=3.8.1)
Provides-Extra: test
Requires-Dist: pytest ; extra == 'test'
Requires-Dist: coverage ; extra == 'test'
Requires-Dist: flake8 ; extra == 'test'
Requires-Dist: black ; extra == 'test'
Requires-Dist: isort ; extra == 'test'
Requires-Dist: pytest-cov ; extra == 'test'
Requires-Dist: codecov ; extra == 'test'
Requires-Dist: mypy ; extra == 'test'
Requires-Dist: gitchangelog ; extra == 'test'
Requires-Dist: mkdocs ; extra == 'test'
Requires-Dist: pydantic (~=1.9.1) ; extra == 'test'
Requires-Dist: aiohttp (~=3.8.1) ; extra == 'test'
